pynetro/__init__.py
pynetro/client.py
pynetro/http.py
pynetro-0.1.5.dist-info/licenses/LICENSE
pynetro-0.1.5.dist-info/METADATA
pynetro-0.1.5.dist-info/WHEEL
pynetro-0.1.5.dist-info/top_level.txt
pynetro-0.1.5.dist-info/RECORD
