Metadata-Version: 2.4
Name: pynetro
Version: 0.1.5
Summary: Async Python wrapper for Netro API (HTTP-agnostic, HA-friendly)
Author-email: kcofoni <kcofoni@gmail.com>
License: MIT
Project-URL: Homepage, https://github.com/kcofoni/pynetro
Project-URL: Repository, https://github.com/kcofoni/pynetro
Project-URL: Issues, https://github.com/kcofoni/pynetro/issues
Project-URL: Documentation, https://github.com/kcofoni/pynetro#readme
Keywords: netro,irrigation,asyncio,home-assistant,api
Classifier: Development Status :: 3 - Alpha
Classifier: Intended Audience :: Developers
Classifier: Topic :: Home Automation
Classifier: Topic :: Software Development :: Libraries :: Python Modules
Classifier: Programming Language :: Python :: 3
Classifier: Programming Language :: Python :: 3.10
Classifier: Programming Language :: Python :: 3.11
Classifier: Programming Language :: Python :: 3.12
Classifier: Framework :: AsyncIO
Classifier: License :: OSI Approved :: MIT License
Classifier: Operating System :: OS Independent
Requires-Python: >=3.10
License-File: LICENSE
Dynamic: license-file
